supervisor_stdlog.py
supervisor_stdlog-0.7.9.dist-info/LICENSE.md
supervisor_stdlog-0.7.9.dist-info/METADATA
supervisor_stdlog-0.7.9.dist-info/WHEEL
supervisor_stdlog-0.7.9.dist-info/entry_points.txt
supervisor_stdlog-0.7.9.dist-info/top_level.txt
supervisor_stdlog-0.7.9.dist-info/RECORD
